conformal_drift/__init__.py
conformal_drift/auditor.py
conformal_drift/cli.py
conformal_drift/metrics.py
conformal_drift/shifts.py
conformal_drift-0.1.0.dist-info/licenses/LICENSE
tests/__init__.py
tests/test_auditor.py
tests/test_metrics.py
conformal_drift-0.1.0.dist-info/METADATA
conformal_drift-0.1.0.dist-info/WHEEL
conformal_drift-0.1.0.dist-info/entry_points.txt
conformal_drift-0.1.0.dist-info/top_level.txt
conformal_drift-0.1.0.dist-info/RECORD
