Metadata-Version: 2.4
Name: conformal-drift
Version: 0.1.0
Summary: Audit protocol for stress-testing conformal prediction guardrails under distribution shift
Author-email: Debu Sinha <debusinha2009@gmail.com>
Maintainer-email: Debu Sinha <debusinha2009@gmail.com>
License: MIT
Project-URL: Homepage, https://github.com/debu-sinha/conformaldrift
Project-URL: Documentation, https://github.com/debu-sinha/conformaldrift#readme
Project-URL: Repository, https://github.com/debu-sinha/conformaldrift
Project-URL: Issues, https://github.com/debu-sinha/conformaldrift/issues
Project-URL: Changelog, https://github.com/debu-sinha/conformaldrift/blob/main/CHANGELOG.md
Keywords: conformal-prediction,distribution-shift,rag,hallucination-detection,uncertainty-quantification,nlp,machine-learning,ai-safety,calibration,guardrails
Classifier: Development Status :: 4 - Beta
Classifier: Intended Audience :: Science/Research
Classifier: Intended Audience :: Developers
Classifier: License :: OSI Approved :: MIT License
Classifier: Operating System :: OS Independent
Classifier: Programming Language :: Python :: 3
Classifier: Programming Language :: Python :: 3.8
Classifier: Programming Language :: Python :: 3.9
Classifier: Programming Language :: Python :: 3.10
Classifier: Programming Language :: Python :: 3.11
Classifier: Programming Language :: Python :: 3.12
Classifier: Topic :: Scientific/Engineering :: Artificial Intelligence
Classifier: Topic :: Software Development :: Libraries :: Python Modules
Classifier: Typing :: Typed
Requires-Python: >=3.8
License-File: LICENSE
Requires-Dist: numpy>=1.20.0
Requires-Dist: scipy>=1.7.0
Provides-Extra: dev
Requires-Dist: pytest>=7.0.0; extra == "dev"
Requires-Dist: pytest-cov>=4.0.0; extra == "dev"
Requires-Dist: black>=23.0.0; extra == "dev"
Requires-Dist: ruff>=0.1.0; extra == "dev"
Requires-Dist: mypy>=1.0.0; extra == "dev"
Requires-Dist: pre-commit>=3.0.0; extra == "dev"
Provides-Extra: full
Requires-Dist: torch>=1.10.0; extra == "full"
Requires-Dist: transformers>=4.20.0; extra == "full"
Requires-Dist: datasets>=2.0.0; extra == "full"
Requires-Dist: sentence-transformers>=2.2.0; extra == "full"
Provides-Extra: docs
Requires-Dist: mkdocs>=1.5.0; extra == "docs"
Requires-Dist: mkdocs-material>=9.0.0; extra == "docs"
Requires-Dist: mkdocstrings[python]>=0.24.0; extra == "docs"
Dynamic: license-file
